nonebot_plugin_all4one-0.1.0a4.dist-info/METADATA
nonebot_plugin_all4one-0.1.0a4.dist-info/WHEEL
nonebot_plugin_all4one-0.1.0a4.dist-info/licenses/LICENSE
nonebot_plugin_all4one/__init__.py
nonebot_plugin_all4one/database/__init__.py
nonebot_plugin_all4one/database/fleep.json
nonebot_plugin_all4one/database/fleep.py
nonebot_plugin_all4one/middlewares/__init__.py
nonebot_plugin_all4one/middlewares/base.py
nonebot_plugin_all4one/middlewares/discord.py
nonebot_plugin_all4one/middlewares/onebot_v11.py
nonebot_plugin_all4one/middlewares/qqguild.py
nonebot_plugin_all4one/middlewares/telegram.py
nonebot_plugin_all4one/migrations/6e6321bc6c48_init_db.py
nonebot_plugin_all4one/migrations/d0a1d19f3408_.py
nonebot_plugin_all4one/onebotimpl/__init__.py
nonebot_plugin_all4one/onebotimpl/config.py
nonebot_plugin_all4one/onebotimpl/utils.py
nonebot_plugin_all4one-0.1.0a4.dist-info/RECORD
