Metadata-Version: 2.1
Name: nonebot-plugin-all4one
Version: 0.1.0a4
Summary: Make NoneBot as OneBot Implementation
Author-Email: Jigsaw <j1g5awi@proton.me>
License: AGPL-3.0-only
Requires-Python: <4.0,>=3.9
Requires-Dist: nonebot2<3.0.0,>=2.2.1
Requires-Dist: nonebot-adapter-onebot>=2.2.2
Requires-Dist: nonebot-plugin-localstore>=0.7.1
Requires-Dist: nonebot-plugin-orm>=0.7.5
Requires-Dist: pydantic>=2.6.4
Requires-Dist: httpx>=0.27.0
Requires-Dist: nonebot-adapter-telegram>=0.1.0b13; extra == "telegram"
Requires-Dist: nonebot-adapter-qq>=0.2.2; extra == "qq"
Requires-Dist: nonebot-adapter-discord>=0.1.8; extra == "discord"
Requires-Dist: nonebot-adapter-telegram>=0.1.0b13; extra == "adapters"
Requires-Dist: nonebot-adapter-qq>=0.2.4; extra == "adapters"
Requires-Dist: nonebot-adapter-discord>=0.1.8; extra == "adapters"
Provides-Extra: telegram
Provides-Extra: qq
Provides-Extra: discord
Provides-Extra: adapters
